{"name":"HQH","created_at":"12/02/2015 06:01:12 p.m.","updated_at":"12/02/2015 06:01:12 p.m."}{"name":"HQH","created_at":"12/02/2015 06:03:02 p.m.","updated_at":"12/02/2015 06:03:02 p.m."}{"name":"HQH","created_at":"12/02/2015 06:04:35 p.m.","updated_at":"12/02/2015 06:04:35 p.m."}{"name":"HQH","created_at":"12/02/2015 06:29:05 p.m.","updated_at":"12/02/2015 06:29:05 p.m."}{"name":"HQH","created_at":"12/02/2015 06:29:34 p.m.","updated_at":"12/02/2015 06:29:34 p.m."}{"name":"HQH","created_at":"12/02/2015 06:30:15 p.m.","updated_at":"12/02/2015 06:30:15 p.m."}{"name":"HQH","created_at":"12/02/2015 06:30:58 p.m.","updated_at":"12/02/2015 06:30:58 p.m."}{"name":"HQH","created_at":"12/02/2015 06:32:02 p.m.","updated_at":"12/02/2015 06:32:02 p.m."}{"name":"HQH","created_at":"12/02/2015 06:38:27 p.m.","updated_at":"12/02/2015 06:38:27 p.m."}{"name":"HQH","created_at":"12/02/2015 06:40:24 p.m.","updated_at":"12/02/2015 06:40:24 p.m."}{"name":"HQH","created_at":"12/02/2015 06:43:32 p.m.","updated_at":"12/02/2015 06:43:32 p.m."}{"name":"HQH","created_at":"12/02/2015 06:44:58 p.m.","updated_at":"12/02/2015 06:44:58 p.m."}{"name":"HQH","created_at":"12/02/2015 06:50:45 p.m.","updated_at":"12/02/2015 06:50:45 p.m."}{"name":"HQH","created_at":"12/02/2015 06:51:15 p.m.","updated_at":"12/02/2015 06:51:15 p.m."}